universal_profanity/__init__.py
universal_profanity/_patterns.py
universal_profanity/profanity.py
universal_profanity-0.1.0.dist-info/LICENSE
universal_profanity-0.1.0.dist-info/METADATA
universal_profanity-0.1.0.dist-info/WHEEL
universal_profanity-0.1.0.dist-info/top_level.txt
universal_profanity-0.1.0.dist-info/RECORD
