Metadata-Version: 2.1
Name: universal-profanity
Version: 0.1.0
Summary: Python library for text censoring in multiple languages
Home-page: UNKNOWN
Author: DillerDurak
License: UNKNOWN
Platform: UNKNOWN
License-File: LICENSE
